tests/__init__.py
tests/tests.py
tests/__pycache__/__init__.cpython-310.pyc
tests/__pycache__/tests.cpython-310-pytest-7.2.0.pyc
tests/__pycache__/tests.cpython-310.pyc
yahoostats/__init__.py
yahoostats/evaluator.py
yahoostats/logger.py
yahoostats/morningstars.py
yahoostats/morningstars_db.json
yahoostats/reuters.py
yahoostats/seeking_alpha.py
yahoostats/simplywall.py
yahoostats/simplywall_db.json
yahoostats/tipranks.py
yahoostats/utils.py
yahoostats/yahoo.py
yahoostats/zacks.py
yahoostats/__pycache__/__init__.cpython-310.pyc
yahoostats/__pycache__/evaluator.cpython-310.pyc
yahoostats/__pycache__/logger.cpython-310.pyc
yahoostats/__pycache__/morningstars.cpython-310.pyc
yahoostats/__pycache__/requests_stats.cpython-310.pyc
yahoostats/__pycache__/reuters.cpython-310.pyc
yahoostats/__pycache__/seeking_alpha.cpython-310.pyc
yahoostats/__pycache__/selenium_stats.cpython-310.pyc
yahoostats/__pycache__/simplywall.cpython-310.pyc
yahoostats/__pycache__/tipranks.cpython-310.pyc
yahoostats/__pycache__/utils.cpython-310.pyc
yahoostats/__pycache__/yahoo.cpython-310.pyc
yahoostats/__pycache__/zacks.cpython-310.pyc
yahoostats-0.0.5.dist-info/LICENSE.txt
yahoostats-0.0.5.dist-info/METADATA
yahoostats-0.0.5.dist-info/WHEEL
yahoostats-0.0.5.dist-info/top_level.txt
yahoostats-0.0.5.dist-info/RECORD
