Metadata-Version: 2.1
Name: yahoostats
Version: 0.0.5
Summary: Yahoo statistics webscraper
Home-page: https://github.com/hristo-mavrodiev/yahoostats
Author: Hristo Mavrodiev
Author-email: h.mavrodiev@abv.bg
Project-URL: Bug Reports, https://github.com/hristo-mavrodiev/yahoostats/issues
Project-URL: Source, https://github.com/hristo-mavrodiev/yahoostats
Classifier: Development Status :: 3 - Alpha
Classifier: Programming Language :: Python :: 3.6
Classifier: Programming Language :: Python :: 3.7
Classifier: Programming Language :: Python :: 3.8
Classifier: License :: OSI Approved :: MIT License
Classifier: Operating System :: OS Independent
Requires-Python: >=3.6
License-File: LICENSE.txt
Requires-Dist: pandas (>=1.5.2)
Requires-Dist: requests (>=2.28.1)
Requires-Dist: tenacity (>=8.1.0)
Requires-Dist: bs4 (>=0.0.1)
Requires-Dist: beautifulsoup4 (>=4.11.1)
